LICENSE
MANIFEST.in
README.rst
setup.cfg
setup.py
DUlib.egg-info/PKG-INFO
DUlib.egg-info/SOURCES.txt
DUlib.egg-info/dependency_links.txt
DUlib.egg-info/entry_points.txt
DUlib.egg-info/not-zip-safe
DUlib.egg-info/top_level.txt
du/__init__.py
du/_pydoc.py
du/examples.py
du/highlight.py
du/lib.py
du/models.py
du/utils.py
du/conv/__init__.py
du/conv/examples.py
du/conv/models.py
du/rec/__init__.py
du/rec/examples.py
du/rec/lib.py
du/rec/models.py