Metadata-Version: 1.2
Name: DUlib
Version: 0.9.3
Summary: tools from The DL@DU Project
Home-page: https://github.com/sj-simmons/DUlib
Author: Scott Simmons
Author-email: ssimmons@drury.edu
License: Apache 2.0
Download-URL: https://github.com/sj-simmons/DUlib/archive/v0.4.tar.gz
Project-URL: Upstream Repository, https://github.com/sj-simmons/DUlib
Platform: UNKNOWN
Classifier: Development Status :: 4 - Beta
Classifier: Intended Audience :: Developers
Classifier: Intended Audience :: Science/Research
Classifier: Intended Audience :: Education
Classifier: Programming Language :: Python :: 3.5
Classifier: Programming Language :: Python :: 3.6
Classifier: Programming Language :: Python :: 3.7
Classifier: Programming Language :: Python :: 3.8
Classifier: Topic :: Scientific/Engineering
Classifier: Topic :: Scientific/Engineering :: Mathematics
Classifier: Topic :: Scientific/Engineering :: Artificial Intelligence
Classifier: Topic :: Software Development :: Libraries
Classifier: Topic :: Software Development :: Libraries :: Python Modules
Classifier: Topic :: Software Development
Classifier: License :: OSI Approved :: Apache Software License
Requires-Python: >=3.5
